pyfract/__init__.py
pyfract/fraction.py
pyfract/src/__init__.py
pyfract/src/utils.py
pyfract-1.4.1.dist-info/LICENSE
pyfract-1.4.1.dist-info/LICENSE.txt
pyfract-1.4.1.dist-info/METADATA
pyfract-1.4.1.dist-info/WHEEL
pyfract-1.4.1.dist-info/top_level.txt
pyfract-1.4.1.dist-info/RECORD
