Metadata-Version: 2.1
Name: pyfract
Version: 1.4.1
Summary: Fractions implementation for Python
Home-page: https://github.com/wblazej/pyfract
Author: Błażej Wrzosok
License: MIT
Keywords: math,fractions,fract,numerator,denominator
Platform: UNKNOWN
Classifier: Development Status :: 4 - Beta
Classifier: Intended Audience :: Developers
Classifier: License :: OSI Approved :: MIT License
Classifier: Programming Language :: Python :: 3
Classifier: Programming Language :: Python :: 3.4
Classifier: Programming Language :: Python :: 3.5
Classifier: Programming Language :: Python :: 3.6
Classifier: Programming Language :: Python :: 3.7
Classifier: Programming Language :: Python :: 3.8
Classifier: Programming Language :: Python :: 3.9
License-File: LICENSE
License-File: LICENSE.txt
